taskquant/__init__.py
taskquant/__main__.py
taskquant/app.py
taskquant/score/__init__.py
taskquant/score/accum.py
taskquant/utils/__init__.py
taskquant/utils/colors.py
taskquant/utils/create_table.py
taskquant/utils/helpful.py
taskquant-0.0.5.dist-info/LICENSE
taskquant-0.0.5.dist-info/METADATA
taskquant-0.0.5.dist-info/WHEEL
taskquant-0.0.5.dist-info/entry_points.txt
taskquant-0.0.5.dist-info/top_level.txt
taskquant-0.0.5.dist-info/RECORD
