Metadata-Version: 2.1
Name: taskquant
Version: 0.0.5
Summary: A python CLI that extends taskwarrior for productivity scoreboard & gamification (quantified self)
Home-page: https://github.com/onlyphantom/taskquant
Author: Samuel Chan
Author-email: s@supertype.ai
License: MIT
Platform: UNKNOWN
Classifier: License :: OSI Approved :: MIT License
Classifier: Programming Language :: Python :: 3
Classifier: Programming Language :: Python :: 3.7
Classifier: Operating System :: OS Independent
Requires-Python: >=3.7
License-File: LICENSE
Requires-Dist: tasklib
